craftercms_sphinx_theme/__init__.py
craftercms_sphinx_theme/breadcrumbs.html
craftercms_sphinx_theme/layout.html
craftercms_sphinx_theme/search.html
craftercms_sphinx_theme/theme.conf
craftercms_sphinx_theme/static/css/app.css
craftercms_sphinx_theme/static/img/crafter-logo-white.png
craftercms_sphinx_theme/static/js/app.js
craftercms_sphinx_theme-1.1.4.dist-info/DESCRIPTION.rst
craftercms_sphinx_theme-1.1.4.dist-info/METADATA
craftercms_sphinx_theme-1.1.4.dist-info/RECORD
craftercms_sphinx_theme-1.1.4.dist-info/WHEEL
craftercms_sphinx_theme-1.1.4.dist-info/entry_points.txt
craftercms_sphinx_theme-1.1.4.dist-info/metadata.json
craftercms_sphinx_theme-1.1.4.dist-info/top_level.txt
